project_manager/__init__.py
project_manager/commands/__init__.py
project_manager/commands/build.py
project_manager/commands/gather.py
project_manager/commands/run.py
project_manager/config_validation.py
project_manager/main.py
project_manager/tests/__init__.py
project_manager/tests/config.yaml
project_manager/tests/dummy_project/my_conf.yaml
project_manager/tests/dummy_project/run.py
project_manager/tests/test_config_validation.py
project_manager/tests/test_integration.py
project_manager/utils.py
project_manager-0.2.0.dist-info/entry_points.txt
project_manager-0.2.0.dist-info/WHEEL
project_manager-0.2.0.dist-info/METADATA
project_manager-0.2.0.dist-info/RECORD
